klarfrs-0.2.0.dist-info/METADATA
klarfrs-0.2.0.dist-info/WHEEL
klarfrs-0.2.0.dist-info/licenses/LICENSE
klarfrs/__init__.py
klarfrs/klarfrs.cpython-310-x86_64-linux-gnu.so
klarfrs-0.2.0.dist-info/RECORD
