Metadata-Version: 2.3
Name: klarfrs
Version: 0.2.0
Classifier: Programming Language :: Rust
Classifier: Programming Language :: Python :: Implementation :: CPython
Classifier: Programming Language :: Python :: Implementation :: PyPy
License-File: LICENSE
Summary: Klarfrs is a parser written in Rust to read klarf files as a python dictionary. Currently it only supports version 1.2.
Keywords: parser,rust-lang,semiconductor,klarf,wafers
Author-email: Norman Banick <norman.banick@gmail.com>
Requires-Python: >=3.9
Project-URL: Homepage, https://github.com/banickn/klarfrs
Project-URL: Repository, https://github.com/banickn/klarfrs
